ge_custom_slack_renderer/__init__.py
ge_custom_slack_renderer/custom_slack_renderer.py
ge_custom_slack_renderer-0.1.1.dist-info/WHEEL
ge_custom_slack_renderer-0.1.1.dist-info/METADATA
ge_custom_slack_renderer-0.1.1.dist-info/RECORD
